dirprintly/__init__.py
dirprintly/file_printer.py
dirprintly-1.3.4.dist-info/LICENSE
dirprintly-1.3.4.dist-info/METADATA
dirprintly-1.3.4.dist-info/WHEEL
dirprintly-1.3.4.dist-info/entry_points.txt
dirprintly-1.3.4.dist-info/top_level.txt
dirprintly-1.3.4.dist-info/RECORD
