Metadata-Version: 2.1
Name: dirprintly
Version: 1.3.4
Summary: 📂 Easily view file contents in your terminal with a simple command. No need to open an editor! 💻
Home-page: https://github.com/PasanAbeysekara/dirprintly
Author: Pasan Abeysekara
Author-email: pasankavindaabey@gmail.com
Project-URL: Bug Tracker, https://github.com/PasanAbeysekara/dirprintly/issues
License-File: LICENSE
Requires-Dist: colorama
